{
	"id": "zenhosta-gratis-domain-1-tahun",
	"title": "Gratis Domain 1 Tahun Walau Order Hosting 1 Bulan",
	"provider": "Zenhosta",
	"description": "Zenhosta memberikan gratis domain selama 1 tahun untuk pengguna yang melakukan order hosting, bahkan cukup dengan memilih paket hosting bulanan.",
	"benefits": [
		"Gratis domain selama 1 tahun",
		"Bisa didapatkan hanya dengan order hosting 1 bulan",
		"Pilihan domain gratis tersedia untuk ekstensi .my.id, .web.id, dan .biz.id"
	],
	"requirements": [
		"Masuk ke halaman https://zenhosta.com/hosting",
		"Pilih paket hosting, bisa menggunakan paket paling murah.",
		"Pilih opsi \"Gratis Domain\".",
		"Pilih domain gratis yang tersedia, yaitu .my.id, .web.id, atau .biz.id.",
		"Selesaikan pembayaran, lalu pengguna akan mendapatkan hosting + free domain selama 1 tahun."
	],
	"validity": {
		"type": "fixed",
		"date": "2026-12-31",
		"description": "Promo berlaku sampai 31 Desember 2026."
	},
	"ctaLink": "https://zenhosta.com/member/aff.php?aff=20",
	"tags": ["Hosting", "Domain", "Cloud Services"],
	"status": "active",
	"featured": false,
	"tips": "Pastikan memilih opsi \"Gratis Domain\" saat proses order dan memilih ekstensi domain yang termasuk promo, yaitu .my.id, .web.id, atau .biz.id.",
	"publishedAt": "2026-07-01",
	"source": "https://zenhosta.com/hosting",
	"contributorSlug": "ogya-adyatma-putra"
}
